gcb202h23/__init__.py
gcb202h23/data.pkl
gcb202h23-0.3.dist-info/METADATA
gcb202h23-0.3.dist-info/WHEEL
gcb202h23-0.3.dist-info/top_level.txt
gcb202h23-0.3.dist-info/RECORD
